dpsbin/__init__.py
dpsbin/_exact.py
dpsbin/_monte.py
dpsbin/test_implementations_agree.py
dpsbin-0.0.4.dist-info/LICENSE.txt
dpsbin-0.0.4.dist-info/METADATA
dpsbin-0.0.4.dist-info/WHEEL
dpsbin-0.0.4.dist-info/top_level.txt
dpsbin-0.0.4.dist-info/RECORD
