Metadata-Version: 2.1
Name: dpsbin
Version: 0.0.4
Summary: Compute exact DPS for turn-based games
Home-page: https://github.com/hmusgrave/dpsbin
Author: Hans Musgrave
Author-email: Hans.Musgrave@gmail.com
License: UNKNOWN
Download-URL: https://github.com/hmusgrave/dpsbin/archive/0.0.4.tar.gz
Platform: UNKNOWN
Classifier: Programming Language :: Python :: 3
Classifier: License :: OSI Approved :: GNU Affero General Public License v3 or later (AGPLv3+)
Classifier: Operating System :: OS Independent
Requires-Python: >=3
Requires-Dist: numpy
Requires-Dist: scipy (>=1.0.0)
